GOL_Simulator/__init__.py
GOL_Simulator/cpu.py
GOL_Simulator/gpu.py
GOL_Simulator-0.0.3.dist-info/METADATA
GOL_Simulator-0.0.3.dist-info/WHEEL
GOL_Simulator-0.0.3.dist-info/top_level.txt
GOL_Simulator-0.0.3.dist-info/zip-safe
GOL_Simulator-0.0.3.dist-info/RECORD
